nlpboost/__init__.py
nlpboost/autotrainer.py
nlpboost/ckpt_cleaner.py
nlpboost/dataset_config.py
nlpboost/default_param_spaces.py
nlpboost/hfdatasets_manager.py
nlpboost/hftransformers_manager.py
nlpboost/metrics.py
nlpboost/metrics_plotter.py
nlpboost/model_config.py
nlpboost/results_getter.py
nlpboost/skip_mix.py
nlpboost/tokenization_functions.py
nlpboost/utils.py
nlpboost/augmentation/TextAugmenterPipeline.py
nlpboost/augmentation/__init__.py
nlpboost/augmentation/augmenter_config.py
nlpboost-0.0.1.dist-info/LICENSE.md
nlpboost-0.0.1.dist-info/METADATA
nlpboost-0.0.1.dist-info/WHEEL
nlpboost-0.0.1.dist-info/top_level.txt
nlpboost-0.0.1.dist-info/RECORD
