Metadata-Version: 2.1
Name: nlpboost
Version: 0.0.1
Summary: A package for automatic training of NLP (transformers) models
Home-page: https://github.com/avacaondata/nlpboost
Author: Alejandro Vaca Serrano
Author-email: alejandro_vaca0@hotmail.com
Keywords: natural-language-processing,nlp,transformers,hyperparameter-tuning,automatic-training
Classifier: Development Status :: 5 - Production/Stable
Classifier: Intended Audience :: Science/Research
Classifier: Operating System :: OS Independent
Classifier: Programming Language :: Python
Classifier: Programming Language :: Python :: 3 :: Only
Classifier: Programming Language :: Python :: 3.7
Classifier: Programming Language :: Python :: 3.8
Classifier: Programming Language :: Python :: 3.9
Classifier: Programming Language :: Python :: 3.10
Classifier: Topic :: Scientific/Engineering
Requires-Python: >=3.9.13,<3.11
License-File: LICENSE.md
Requires-Dist: transformers[torch] (>=4.16)
Requires-Dist: datasets (>=1.11.0)
Requires-Dist: optuna (>=3.0.2)
Requires-Dist: scikit-learn (>=1.0.2)
Requires-Dist: nltk (==3.7)
Requires-Dist: rouge-score (==0.1.2)
Requires-Dist: tensorboard (==2.10.1)
Requires-Dist: tensorboardX (==2.5.1)
Requires-Dist: sentencepiece (==0.1.97)
Requires-Dist: apscheduler (==3.6.3)
Requires-Dist: seaborn (==0.12.0)
Requires-Dist: nlpaug (==1.1.11)
Requires-Dist: simpletransformers (>=0.61.10)
Requires-Dist: pandas (>=1.3.5)
Requires-Dist: tqdm (==4.64.1)
Requires-Dist: evaluate (==0.2.2)
Requires-Dist: more-itertools (==8.14.0)
Requires-Dist: polyfuzz (==0.4.0)
Requires-Dist: seqeval (==1.2.2)
Requires-Dist: sphinxemoji (==0.2.0)
Requires-Dist: pytest (==7.1.3)
Requires-Dist: sphinx (==5.3.0)
Requires-Dist: sphinx-rtd-theme (>=1.1.1)
Requires-Dist: readthedocs-sphinx-search (==0.1.2)
Requires-Dist: sphinxcontrib-applehelp (==1.0.2)
Requires-Dist: sphinxcontrib-devhelp (==1.0.2)
Requires-Dist: sphinxcontrib-htmlhelp (==2.0.0)
Requires-Dist: sphinxcontrib-jsmath (==1.0.1)
Requires-Dist: sphinxcontrib-qthelp (==1.0.3)
Requires-Dist: sphinxcontrib-serializinghtml (==1.1.5)
Requires-Dist: numpydoc (==1.5.0)
